ewf_mount/__init__.py
ewf_mount/script.py
py_ewf_mount-1.0.0.dist-info/LICENSE
py_ewf_mount-1.0.0.dist-info/METADATA
py_ewf_mount-1.0.0.dist-info/WHEEL
py_ewf_mount-1.0.0.dist-info/entry_points.txt
py_ewf_mount-1.0.0.dist-info/top_level.txt
py_ewf_mount-1.0.0.dist-info/RECORD
