Metadata-Version: 2.1
Name: py-ewf-mount
Version: 1.0.0
Summary: A cli wrapper script to mount EWF files.
Home-page: https://github.com/wahlflo/pyEWFmount
Author: Florian Wahl
Author-email: florian.wahl.developer@gmail.com
License: UNKNOWN
Platform: UNKNOWN
Classifier: Programming Language :: Python :: 3
Classifier: License :: OSI Approved :: MIT License
Classifier: Operating System :: Unix
Requires-Dist: cli-formatter
